{
  "results": [
    {
        "business_status": "OPERATIONAL",
        "geometry": {
            "location": {
                "lat": 10.3313256,
                "lng": 123.9026801
            },
            "viewport": {
                "northeast": {
                    "lat": 10.3325823302915,
                    "lng": 123.9039675802915
                },
                "southwest": {
                    "lat": 10.3298843697085,
                    "lng": 123.9012696197085
                }
            }
        },
        "icon": "https://maps.gstatic.com/mapfiles/place_api/icons/v1/png_71/lodging-71.png",
        "icon_background_color": "#909CE1",
        "icon_mask_base_uri": "https://maps.gstatic.com/mapfiles/place_api/icons/v2/hotel_pinlet",
        "name": "Metro Park Hotel - Cebu City",
        "opening_hours": {
            "open_now": false
        },
        "photos": [
            {
                "height": 810,
                "html_attributions": [
                    "<a href=\"https://maps.google.com/maps/contrib/109306137821316126816\">Metro Park Hotel - Cebu City</a>"
                ],
                "photo_reference": "ATJ83zjnjINfW6HbRGAyMbzr6k8VQZU76ouU8e5SU0kgRqK_HO9osgPk0PS-hd8xsoo_m_ZJ6TRGtchLHcao0q7IommuE3mpPLkCbK9F4aWx5g5m-Q0zFliu-5S9WUg3hWPs3cA3yi2nJs2LnE88rdicWrWEQAbdQ0XCD5t5wbzQkUzlT4bF",
                "width": 1440
            }
        ],
        "place_id": "ChIJ4Vm4siaZqTMRISv16iNQN58",
        "plus_code": {
            "compound_code": "8WJ3+G3 Cebu City, Cebu, Philippines",
            "global_code": "7Q258WJ3+G3"
        },
        "rating": 3.3,
        "reference": "ChIJ4Vm4siaZqTMRISv16iNQN58",
        "scope": "GOOGLE",
        "types": [
            "lodging",
            "restaurant",
            "food",
            "point_of_interest",
            "health",
            "establishment"
        ],
        "user_ratings_total": 66,
        "vicinity": "Saint Lawrence Street, La Guardia Street, Cebu City"
    },
    {
        "business_status": "OPERATIONAL",
        "geometry": {
            "location": {
                "lat": 10.320089,
                "lng": 123.9014872
            },
            "viewport": {
                "northeast": {
                    "lat": 10.3213955302915,
                    "lng": 123.9028826302915
                },
                "southwest": {
                    "lat": 10.3186975697085,
                    "lng": 123.9001846697085
                }
            }
        },
        "icon": "https://maps.gstatic.com/mapfiles/place_api/icons/v1/png_71/lodging-71.png",
        "icon_background_color": "#909CE1",
        "icon_mask_base_uri": "https://maps.gstatic.com/mapfiles/place_api/icons/v2/hotel_pinlet",
        "name": "Wellcome Hotel",
        "opening_hours": {
            "open_now": true
        },
        "photos": [
            {
                "height": 3456,
                "html_attributions": [
                    "<a href=\"https://maps.google.com/maps/contrib/114180255521344011769\">Wellcome Hotel</a>"
                ],
                "photo_reference": "ATJ83zjutmK2XxfYZCvjNLBIz2JQvWaHnxcBpv3y4vKQdYHgHkYH-lTBpXGsmkRPgVlX112yjjylesziXg4WytOhw1ma9S6zTvm2-JHaJAzBegI1eGdsXCIOkbhGgCJXXD4W3IK811xsWdKGR_-JAFyoVU6QaTj9MTO9-EzRquh55eiAGbrS",
                "width": 5184
            }
        ],
        "place_id": "ChIJU1O8RTmZqTMRvo6rDn8dQKM",
        "plus_code": {
            "compound_code": "8WC2+2H Cebu City, Cebu, Philippines",
            "global_code": "7Q258WC2+2H"
        },
        "rating": 4,
        "reference": "ChIJU1O8RTmZqTMRvo6rDn8dQKM",
        "scope": "GOOGLE",
        "types": [
            "lodging",
            "restaurant",
            "food",
            "point_of_interest",
            "establishment"
        ],
        "user_ratings_total": 582,
        "vicinity": "18 Molave Street, Cebu City"
    },
    {
        "business_status": "OPERATIONAL",
        "geometry": {
            "location": {
                "lat": 10.32975,
                "lng": 123.9016647
            },
            "viewport": {
                "northeast": {
                    "lat": 10.3309684802915,
                    "lng": 123.9029442302915
                },
                "southwest": {
                    "lat": 10.3282705197085,
                    "lng": 123.9002462697085
                }
            }
        },
        "icon": "https://maps.gstatic.com/mapfiles/place_api/icons/v1/png_71/lodging-71.png",
        "icon_background_color": "#909CE1",
        "icon_mask_base_uri": "https://maps.gstatic.com/mapfiles/place_api/icons/v2/hotel_pinlet",
        "name": "Crowne Garden Hotel",
        "opening_hours": {
            "open_now": true
        },
        "photos": [
            {
                "height": 1075,
                "html_attributions": [
                    "<a href=\"https://maps.google.com/maps/contrib/106854567279523218031\">Aly</a>"
                ],
                "photo_reference": "ATJ83zioaBdQOABwB6e68tKQY_dsRkm2fcqZa6tps796LtS2NyDMQ1s6ihLvVLXdrkY9AanaDmPM-5nJnfxGLer0BLAwjZfzn2MG9zsWprcLRIpL6ezmwtVC20CSW8maQalM0HD0iWBIismcIwoEi1QS04QGnKispF2_GxZp3TSdh6CL7bK5",
                "width": 1845
            }
        ],
        "place_id": "ChIJO7I8ESSZqTMRsjABytp4VdE",
        "plus_code": {
            "compound_code": "8WH2+WM Cebu City, Cebu, Philippines",
            "global_code": "7Q258WH2+WM"
        },
        "rating": 3.7,
        "reference": "ChIJO7I8ESSZqTMRsjABytp4VdE",
        "scope": "GOOGLE",
        "types": [
            "lodging",
            "restaurant",
            "food",
            "point_of_interest",
            "establishment"
        ],
        "user_ratings_total": 250,
        "vicinity": "Salinas Drive, Cebu City"
    },
    {
        "business_status": "OPERATIONAL",
        "geometry": {
            "location": {
                "lat": 10.3108396,
                "lng": 123.89231
            },
            "viewport": {
                "northeast": {
                    "lat": 10.3121479802915,
                    "lng": 123.8935370302915
                },
                "southwest": {
                    "lat": 10.3094500197085,
                    "lng": 123.8908390697085
                }
            }
        },
        "icon": "https://maps.gstatic.com/mapfiles/place_api/icons/v1/png_71/lodging-71.png",
        "icon_background_color": "#909CE1",
        "icon_mask_base_uri": "https://maps.gstatic.com/mapfiles/place_api/icons/v2/hotel_pinlet",
        "name": "M Citi Suites",
        "opening_hours": {
            "open_now": true
        },
        "photos": [
            {
                "height": 720,
                "html_attributions": [
                    "<a href=\"https://maps.google.com/maps/contrib/110356110494782814086\">leandro Cabalda</a>"
                ],
                "photo_reference": "ATJ83zgG-DAPm3insfO7o0MP65JLnZJJGMwVm7psT6P4dbez-9-otGpEP21Tvs9zPZnIPbY7pYz6yGfwv6DlanW5EwliziDElDWuAZYE6OTu83MHVk5s6IfL-RMFAt_7OS6ljO-klansGmZLar0kB6rKQ91BqjqG2_YlwfKTYFEw0eRmHsev",
                "width": 1280
            }
        ],
        "place_id": "ChIJMUxTlk6ZqTMRb6rATEaXG2A",
        "rating": 3.9,
        "reference": "ChIJMUxTlk6ZqTMRb6rATEaXG2A",
        "scope": "GOOGLE",
        "types": [
            "cafe",
            "store",
            "lodging",
            "restaurant",
            "food",
            "point_of_interest",
            "establishment"
        ],
        "user_ratings_total": 230,
        "vicinity": "8V6R+8WM, J. Llorente Street, Cebu City"
    },
    {
        "business_status": "OPERATIONAL",
        "geometry": {
            "location": {
                "lat": 10.3193763,
                "lng": 123.903053
            },
            "viewport": {
                "northeast": {
                    "lat": 10.3208364802915,
                    "lng": 123.9045126302915
                },
                "southwest": {
                    "lat": 10.3181385197085,
                    "lng": 123.9018146697085
                }
            }
        },
        "icon": "https://maps.gstatic.com/mapfiles/place_api/icons/v1/png_71/lodging-71.png",
        "icon_background_color": "#909CE1",
        "icon_mask_base_uri": "https://maps.gstatic.com/mapfiles/place_api/icons/v2/hotel_pinlet",
        "name": "Quest Hotel and Conference Center - Cebu",
        "opening_hours": {
            "open_now": true
        },
        "photos": [
            {
                "height": 4256,
                "html_attributions": [
                    "<a href=\"https://maps.google.com/maps/contrib/115853189798090380555\">Quest Hotel and Conference Center - Cebu</a>"
                ],
                "photo_reference": "ATJ83zj3gTyvNdbLZbBrZujx5Y6uEDR5_YPlhahBOdQy3kzSSzNB0OltgTj8BS7OLBg9MV3puOz6LhYyNuHRqZO3xh5insnB2WfVl1inEk6zsdbyZ9paPBLPsf5t_OCI8KMnYprIKRlA3yCcEx5ctwA-8WdkRUQ6rGk0hMc_9sUqb5nNTAg4",
                "width": 2832
            }
        ],
        "place_id": "ChIJm4OrCxSfqTMRLfBAb696MG8",
        "plus_code": {
            "compound_code": "8W93+Q6 Cebu City, Cebu, Philippines",
            "global_code": "7Q258W93+Q6"
        },
        "rating": 4.3,
        "reference": "ChIJm4OrCxSfqTMRLfBAb696MG8",
        "scope": "GOOGLE",
        "types": [
            "lodging",
            "restaurant",
            "food",
            "point_of_interest",
            "establishment"
        ],
        "user_ratings_total": 3687,
        "vicinity": "Archbishop Reyes Avenue, Cebu City"
    },
    {
        "business_status": "OPERATIONAL",
        "geometry": {
            "location": {
                "lat": 10.3247558,
                "lng": 123.9152907
            },
            "viewport": {
                "northeast": {
                    "lat": 10.3260129802915,
                    "lng": 123.9167388802915
                },
                "southwest": {
                    "lat": 10.3233150197085,
                    "lng": 123.9140409197085
                }
            }
        },
        "icon": "https://maps.gstatic.com/mapfiles/place_api/icons/v1/png_71/lodging-71.png",
        "icon_background_color": "#909CE1",
        "icon_mask_base_uri": "https://maps.gstatic.com/mapfiles/place_api/icons/v2/hotel_pinlet",
        "name": "Sarrosa International Hotel & Residential Suites",
        "opening_hours": {
            "open_now": true
        },
        "photos": [
            {
                "height": 3120,
                "html_attributions": [
                    "<a href=\"https://maps.google.com/maps/contrib/107575283700496699015\">ferda küçükçavdar</a>"
                ],
                "photo_reference": "ATJ83zj_wuckavEMTkc0ISgKskW8jNL4FJZWTlI8VyLQ98yQsyOwBkwvQxDTdJIJ6G3rLg22iALmnFc09j1Qu8b9o4ODwBIfE7IvjVT6DE-grrR0xL3yVmdPAXzYHEkQ8Eo0grGgvpnkcEMUjJwvv1wMYRiNTS4eU-H90BWxSNQx4tYf3Vp0",
                "width": 4160
            }
        ],
        "place_id": "ChIJBcCjoBCZqTMR6eiaTPj17po",
        "plus_code": {
            "compound_code": "8WF8+W4 Cebu City, Cebu, Philippines",
            "global_code": "7Q258WF8+W4"
        },
        "rating": 4,
        "reference": "ChIJBcCjoBCZqTMR6eiaTPj17po",
        "scope": "GOOGLE",
        "types": [
            "spa",
            "gym",
            "lodging",
            "restaurant",
            "food",
            "bar",
            "point_of_interest",
            "health",
            "establishment"
        ],
        "user_ratings_total": 776,
        "vicinity": "Ayala access road (axis), Kasambagan, F. Cabahug Street, Cebu City"
    },
    {
        "business_status": "OPERATIONAL",
        "geometry": {
            "location": {
                "lat": 10.3358154,
                "lng": 123.9114026
            },
            "viewport": {
                "northeast": {
                    "lat": 10.3372125302915,
                    "lng": 123.9127677802915
                },
                "southwest": {
                    "lat": 10.3345145697085,
                    "lng": 123.9100698197085
                }
            }
        },
        "icon": "https://maps.gstatic.com/mapfiles/place_api/icons/v1/png_71/lodging-71.png",
        "icon_background_color": "#909CE1",
        "icon_mask_base_uri": "https://maps.gstatic.com/mapfiles/place_api/icons/v2/hotel_pinlet",
        "name": "Main Hotel and Suites",
        "opening_hours": {
            "open_now": true
        },
        "photos": [
            {
                "height": 2250,
                "html_attributions": [
                    "<a href=\"https://maps.google.com/maps/contrib/101374400471396366395\">Philippe Andrei Malvar</a>"
                ],
                "photo_reference": "ATJ83zgC-xgMgRT6QmmcMimb09VLqiPWhN_mn9EH2sJtL4RzTU7loGvF_kThE1iMJ_IB3pW3UurVkZPvGg7h2CMh-WEB9zpBI8dcVepzUxzorzR5Kxew61pMFM-F-ZMNAlgRYOPLUM2xOUjnsHiecXUIG5WJlIY0ut3nH_b66lBldAQKqs6e",
                "width": 4000
            }
        ],
        "place_id": "ChIJpck9uuGYqTMRniQppjWAwZA",
        "rating": 4.1,
        "reference": "ChIJpck9uuGYqTMRniQppjWAwZA",
        "scope": "GOOGLE",
        "types": [
            "cafe",
            "lodging",
            "restaurant",
            "food",
            "point_of_interest",
            "establishment"
        ],
        "user_ratings_total": 343,
        "vicinity": "8WP6+8HC, Cebu City"
    },
    {
        "business_status": "OPERATIONAL",
        "geometry": {
            "location": {
                "lat": 10.3287558,
                "lng": 123.9073391
            },
            "viewport": {
                "northeast": {
                    "lat": 10.3301430802915,
                    "lng": 123.9086198302915
                },
                "southwest": {
                    "lat": 10.3274451197085,
                    "lng": 123.9059218697085
                }
            }
        },
        "icon": "https://maps.gstatic.com/mapfiles/place_api/icons/v1/png_71/restaurant-71.png",
        "icon_background_color": "#FF9E67",
        "icon_mask_base_uri": "https://maps.gstatic.com/mapfiles/place_api/icons/v2/restaurant_pinlet",
        "name": "Chowabungga",
        "opening_hours": {
            "open_now": true
        },
        "photos": [
            {
                "height": 3024,
                "html_attributions": [
                    "<a href=\"https://maps.google.com/maps/contrib/108398615481366842642\">Haavan Havina</a>"
                ],
                "photo_reference": "ATJ83zgpGAzKeMPrqA2JpAkqXyF15lCb33siENtWKHm5W5fNkaR5gatcmdPj02U0vRUoAZxUWitzdnNIEpDW71YV8yz9d9nlxkaNhHts6e6wqkI6-lsJK2eDCWJh6jh3W2SoAT3C-uWkI4Tk6yl6_4OPhIL3mgiW1QL0oJcls_bc0AqRsG9O",
                "width": 4032
            }
        ],
        "place_id": "ChIJj07GFyKZqTMR9WfmA19Mdxw",
        "plus_code": {
            "compound_code": "8WH4+GW Cebu City, Cebu, Philippines",
            "global_code": "7Q258WH4+GW"
        },
        "rating": 4.4,
        "reference": "ChIJj07GFyKZqTMR9WfmA19Mdxw",
        "scope": "GOOGLE",
        "types": [
            "restaurant",
            "food",
            "point_of_interest",
            "establishment"
        ],
        "user_ratings_total": 357,
        "vicinity": "GF i1 Building, Jose Maria del Mar Street, Cebu City"
    },
    {
        "business_status": "OPERATIONAL",
        "geometry": {
            "location": {
                "lat": 10.3425177,
                "lng": 123.9188732
            },
            "viewport": {
                "northeast": {
                    "lat": 10.3439231802915,
                    "lng": 123.9202415802915
                },
                "southwest": {
                    "lat": 10.3412252197085,
                    "lng": 123.9175436197085
                }
            }
        },
        "icon": "https://maps.gstatic.com/mapfiles/place_api/icons/v1/png_71/restaurant-71.png",
        "icon_background_color": "#FF9E67",
        "icon_mask_base_uri": "https://maps.gstatic.com/mapfiles/place_api/icons/v2/restaurant_pinlet",
        "name": "10 Dove's Street Resto",
        "opening_hours": {
            "open_now": false
        },
        "photos": [
            {
                "height": 4000,
                "html_attributions": [
                    "<a href=\"https://maps.google.com/maps/contrib/101231575083316219683\">Shawi Cortez</a>"
                ],
                "photo_reference": "ATJ83zhQKB3Fr6PNXjC24XoEtnUquax9UUhGaFinmj0qfcAbK2q0Am7EcfF2vUOo7sY7z0TufsmGb6QOWFvqdA5mUAAuHzaQdQfYuLHvtcrUuwpjNM2EzwVkM0BbN82XCObzTm_BfVDUoPs089EULqMsCen-2Fh1cO6Q_kpuDBq-WqdiDxMf",
                "width": 2250
            }
        ],
        "place_id": "ChIJDVtYAfKYqTMR_r3HUkk4wCo",
        "plus_code": {
            "compound_code": "8WV9+2G Mandaue City, Cebu, Philippines",
            "global_code": "7Q258WV9+2G"
        },
        "rating": 3.9,
        "reference": "ChIJDVtYAfKYqTMR_r3HUkk4wCo",
        "scope": "GOOGLE",
        "types": [
            "restaurant",
            "food",
            "point_of_interest",
            "establishment"
        ],
        "user_ratings_total": 15,
        "vicinity": "869 A. S. Fortuna Street, Mandaue City"
    },
    {
        "business_status": "OPERATIONAL",
        "geometry": {
            "location": {
                "lat": 10.3189161,
                "lng": 123.9058769
            },
            "viewport": {
                "northeast": {
                    "lat": 10.3203123802915,
                    "lng": 123.9072547302915
                },
                "southwest": {
                    "lat": 10.3176144197085,
                    "lng": 123.9045567697085
                }
            }
        },
        "icon": "https://maps.gstatic.com/mapfiles/place_api/icons/v1/png_71/restaurant-71.png",
        "icon_background_color": "#FF9E67",
        "icon_mask_base_uri": "https://maps.gstatic.com/mapfiles/place_api/icons/v2/restaurant_pinlet",
        "name": "Laguna Garden Café",
        "opening_hours": {
            "open_now": false
        },
        "photos": [
            {
                "height": 3024,
                "html_attributions": [
                    "<a href=\"https://maps.google.com/maps/contrib/116556585191701060546\">Jbulfa</a>"
                ],
                "photo_reference": "ATJ83zi1q0W3fr6spmQL9jzBbvM9H5CicZzto9u-G2ltnyBZSjEqrgs-1K4DsQRu06QKgnDvrdMY9K0VXjRy9ISamciR-M0BXtYCYU0GiJ_LeTNlPfiqTwyTZlAx3wDCUpshFrHvulJALqPSWtkKtUaRCkzD2svPmgNoT2O48aiQsPBEl9hD",
                "width": 4032
            }
        ],
        "place_id": "ChIJzXNlXD6ZqTMRVnTIpSHIBu0",
        "plus_code": {
            "compound_code": "8W94+H9 Cebu City, Cebu, Philippines",
            "global_code": "7Q258W94+H9"
        },
        "price_level": 2,
        "rating": 4.2,
        "reference": "ChIJzXNlXD6ZqTMRVnTIpSHIBu0",
        "scope": "GOOGLE",
        "types": [
            "restaurant",
            "food",
            "point_of_interest",
            "establishment"
        ],
        "user_ratings_total": 342,
        "vicinity": "The Terraces, Ayala Center Cebu, Archbishop Reyes Avenue, Cebu City"
    },
    {
        "business_status": "OPERATIONAL",
        "geometry": {
            "location": {
                "lat": 10.3106654,
                "lng": 123.8930798
            },
            "viewport": {
                "northeast": {
                    "lat": 10.3119902802915,
                    "lng": 123.8943695302915
                },
                "southwest": {
                    "lat": 10.3092923197085,
                    "lng": 123.8916715697085
                }
            }
        },
        "icon": "https://maps.gstatic.com/mapfiles/place_api/icons/v1/png_71/restaurant-71.png",
        "icon_background_color": "#FF9E67",
        "icon_mask_base_uri": "https://maps.gstatic.com/mapfiles/place_api/icons/v2/restaurant_pinlet",
        "name": "McDonald's",
        "opening_hours": {
            "open_now": true
        },
        "photos": [
            {
                "height": 3024,
                "html_attributions": [
                    "<a href=\"https://maps.google.com/maps/contrib/111135516072568211186\">Erickson Gonzales</a>"
                ],
                "photo_reference": "ATJ83zjClraMS0MFpk46UYhEa7w2MS7EHTSni2HMeBXTO84hAusY7UcGyvQOLhHEAzRD6CgtAdkGbUoCdyvwghclsqWLUMpTM_JB96IRdVcRajOXJ685aX1XTgiw0KsZwnF4HpbDEvsX9vz9NVaOumUHu5kP8ATEW-Cb9m3xcU3OIyXdTOW_",
                "width": 4032
            }
        ],
        "place_id": "ChIJG1_gKlCZqTMRcx1TIOTDtXk",
        "plus_code": {
            "compound_code": "8V6V+76 Cebu City, Cebu, Philippines",
            "global_code": "7Q258V6V+76"
        },
        "price_level": 1,
        "rating": 4.1,
        "reference": "ChIJG1_gKlCZqTMRcx1TIOTDtXk",
        "scope": "GOOGLE",
        "types": [
            "restaurant",
            "food",
            "point_of_interest",
            "establishment"
        ],
        "user_ratings_total": 642,
        "vicinity": "Ma. Christina Building, Fuente Osmeña Circle, Cebu City"
    },
    {
        "business_status": "OPERATIONAL",
        "geometry": {
            "location": {
                "lat": 10.3281056,
                "lng": 123.9098361
            },
            "viewport": {
                "northeast": {
                    "lat": 10.3294842302915,
                    "lng": 123.9112223302915
                },
                "southwest": {
                    "lat": 10.3267862697085,
                    "lng": 123.9085243697085
                }
            }
        },
        "icon": "https://maps.gstatic.com/mapfiles/place_api/icons/v1/png_71/restaurant-71.png",
        "icon_background_color": "#FF9E67",
        "icon_mask_base_uri": "https://maps.gstatic.com/mapfiles/place_api/icons/v2/restaurant_pinlet",
        "name": "Abaca Baking Company",
        "opening_hours": {
            "open_now": false
        },
        "photos": [
            {
                "height": 2400,
                "html_attributions": [
                    "<a href=\"https://maps.google.com/maps/contrib/114638588154271600910\">Abaca Baking Company</a>"
                ],
                "photo_reference": "ATJ83ziv-t5e9LBYvQDexE_hpp7Et9FWK0WUav-1o2PZkibKQ6qhk1Gi7rgMj2qDkgZdwcQ1vVeJ3H3CifQbVf-NY7H4_ZicFulND4IA8yaENUU4AlllrjTiflXpB-XtvDd2Ewha0URhk9s0TiaDBKz_xT7ak50LUwXdcNEw69K9GS07FPsi",
                "width": 3600
            }
        ],
        "place_id": "ChIJ4X4i5hiZqTMRbrc4DMK1gXA",
        "plus_code": {
            "compound_code": "8WH5+6W Cebu City, Cebu, Philippines",
            "global_code": "7Q258WH5+6W"
        },
        "price_level": 2,
        "rating": 4.6,
        "reference": "ChIJ4X4i5hiZqTMRbrc4DMK1gXA",
        "scope": "GOOGLE",
        "types": [
            "restaurant",
            "bakery",
            "cafe",
            "store",
            "food",
            "point_of_interest",
            "establishment"
        ],
        "user_ratings_total": 677,
        "vicinity": "Crossroads, Banilad Road, Lungsod ng Cebu"
    },
    {
        "business_status": "OPERATIONAL",
        "geometry": {
            "location": {
                "lat": 10.3004149,
                "lng": 123.8981425
            },
            "viewport": {
                "northeast": {
                    "lat": 10.3017128302915,
                    "lng": 123.8995204802915
                },
                "southwest": {
                    "lat": 10.2990148697085,
                    "lng": 123.8968225197085
                }
            }
        },
        "icon": "https://maps.gstatic.com/mapfiles/place_api/icons/v1/png_71/generic_business-71.png",
        "icon_background_color": "#7B9EB0",
        "icon_mask_base_uri": "https://maps.gstatic.com/mapfiles/place_api/icons/v2/generic_pinlet",
        "name": "Alberto's Pizza",
        "opening_hours": {
            "open_now": true
        },
        "photos": [
            {
                "height": 1944,
                "html_attributions": [
                    "<a href=\"https://maps.google.com/maps/contrib/118041485578436265851\">Inday J</a>"
                ],
                "photo_reference": "ATJ83zi6sPqjWCU4wBEZPePdSycZr2fGpTFcvyg4LED2cgmr3xjz_xUmihzyHk9UW7v-d7rHOVND112bJKgj27tJpJgq8PM72Wd25KmHIjA72A-58-6Hf-ZEIB1xDUbV9atctd_-IlAxCWEb8Kk50KPis0jlttJaelTmCp_u80c-oSehkiNy",
                "width": 1836
            }
        ],
        "place_id": "ChIJpe0YsVmZqTMRZwxhJF3iS5Q",
        "plus_code": {
            "compound_code": "8V2X+57 Cebu City, Cebu, Philippines",
            "global_code": "7Q258V2X+57"
        },
        "price_level": 1,
        "rating": 4,
        "reference": "ChIJpe0YsVmZqTMRZwxhJF3iS5Q",
        "scope": "GOOGLE",
        "types": [
            "meal_delivery",
            "restaurant",
            "food",
            "point_of_interest",
            "establishment"
        ],
        "user_ratings_total": 327,
        "vicinity": "J.T. Montesclaros Bldg. 3, Pantaleon del Rosario Street, Cebu City"
    },
    {
        "business_status": "OPERATIONAL",
        "geometry": {
            "location": {
                "lat": 10.3149181,
                "lng": 123.8954226
            },
            "viewport": {
                "northeast": {
                    "lat": 10.3162117802915,
                    "lng": 123.8967901302915
                },
                "southwest": {
                    "lat": 10.3135138197085,
                    "lng": 123.8940921697085
                }
            }
        },
        "icon": "https://maps.gstatic.com/mapfiles/place_api/icons/v1/png_71/restaurant-71.png",
        "icon_background_color": "#FF9E67",
        "icon_mask_base_uri": "https://maps.gstatic.com/mapfiles/place_api/icons/v2/restaurant_pinlet",
        "name": "Ryan's Pizzarelli House",
        "opening_hours": {
            "open_now": false
        },
        "photos": [
            {
                "height": 1800,
                "html_attributions": [
                    "<a href=\"https://maps.google.com/maps/contrib/106081984709365116768\">Noël</a>"
                ],
                "photo_reference": "ATJ83zgtXEHAqHu9dWaTmlwOI3NeF0tz5C9xIh2-UhkrjRTnpUueZRZdV3rxzaf9G7dPEeEuYY8Lxm6ozYFx3RJejf-pRMB0QGA72Zypls1fi3caM64DF5F-8R9li5eZGwCC6L_fdCt9Kby7GCaBLday5xHFIzUUl0ByM1rluV2JoCPZNeEc",
                "width": 4000
            }
        ],
        "place_id": "ChIJa9yx_kiZqTMRbUWbMp0fOe4",
        "plus_code": {
            "compound_code": "8V7W+X5 Cebu City, Cebu, Philippines",
            "global_code": "7Q258V7W+X5"
        },
        "price_level": 1,
        "rating": 4.5,
        "reference": "ChIJa9yx_kiZqTMRbUWbMp0fOe4",
        "scope": "GOOGLE",
        "types": [
            "restaurant",
            "food",
            "point_of_interest",
            "establishment"
        ],
        "user_ratings_total": 92,
        "vicinity": "F-1, 181 Maria Christina Extension Street, Lungsod ng Cebu"
    },
    {
        "business_status": "OPERATIONAL",
        "geometry": {
            "location": {
                "lat": 10.3093585,
                "lng": 123.89399
            },
            "viewport": {
                "northeast": {
                    "lat": 10.3107682302915,
                    "lng": 123.8952058802915
                },
                "southwest": {
                    "lat": 10.3080702697085,
                    "lng": 123.8925079197085
                }
            }
        },
        "icon": "https://maps.gstatic.com/mapfiles/place_api/icons/v1/png_71/restaurant-71.png",
        "icon_background_color": "#FF9E67",
        "icon_mask_base_uri": "https://maps.gstatic.com/mapfiles/place_api/icons/v2/restaurant_pinlet",
        "name": "Goldilocks",
        "opening_hours": {
            "open_now": false
        },
        "photos": [
            {
                "height": 3024,
                "html_attributions": [
                    "<a href=\"https://maps.google.com/maps/contrib/104164846089820167108\">Alfred Robles</a>"
                ],
                "photo_reference": "ATJ83zgjC2vIhDvGm6ug4Uzw3kX1dKDl_gpYq3rvG8Q4RfBMLGSHzTq6yRm34mLuzeg3ZlQJUkqgNRgkhR-ng30Y4G9O4a9DbiR9CPokp-F64FweMK2-6XEhWD_CdohZBbxWCHUdPCXm9LfI5P7CTLhv9Fhc-HK0nVWmx9koAF1KSdyh5gtO",
                "width": 4032
            }
        ],
        "place_id": "ChIJ5ecdUk6ZqTMRvVIUUqOyHiM",
        "plus_code": {
            "compound_code": "8V5V+PH Cebu City, Cebu, Philippines",
            "global_code": "7Q258V5V+PH"
        },
        "price_level": 2,
        "rating": 4.8,
        "reference": "ChIJ5ecdUk6ZqTMRvVIUUqOyHiM",
        "scope": "GOOGLE",
        "types": [
            "restaurant",
            "food",
            "point_of_interest",
            "establishment"
        ],
        "user_ratings_total": 5,
        "vicinity": "Robinsons Fuente, 6000 Fuente Osmeña Circle, Cebu City"
    },
    {
        "business_status": "OPERATIONAL",
        "geometry": {
            "location": {
                "lat": 10.3184834,
                "lng": 123.9052768
            },
            "viewport": {
                "northeast": {
                    "lat": 10.3201393302915,
                    "lng": 123.9068946302915
                },
                "southwest": {
                    "lat": 10.3174413697085,
                    "lng": 123.9041966697085
                }
            }
        },
        "icon": "https://maps.gstatic.com/mapfiles/place_api/icons/v1/png_71/restaurant-71.png",
        "icon_background_color": "#FF9E67",
        "icon_mask_base_uri": "https://maps.gstatic.com/mapfiles/place_api/icons/v2/restaurant_pinlet",
        "name": "TGI FRIDAYS",
        "opening_hours": {
            "open_now": false
        },
        "photos": [
            {
                "height": 3024,
                "html_attributions": [
                    "<a href=\"https://maps.google.com/maps/contrib/100732656930791181976\">Shane Clark</a>"
                ],
                "photo_reference": "ATJ83ziATuDDgZZG1Tus8-qMk582WqRFDXQVfJd1io_j72fBZGL4PU-Das6nfdnoh1AIlM4NTUekxSgAoYBfXLXXh2VUZpguBDXVr2WEz_S3wYhx4qSXKni7JpsV_Yt4uRJv-8mlrXvnMVTsUCI-cAXltKLc4PgHY01ffOjDFYKVDMA_Mnyf",
                "width": 4032
            }
        ],
        "place_id": "ChIJtbwl9z6ZqTMRre9Ge6vIbz0",
        "plus_code": {
            "compound_code": "8W94+94 Cebu City, Cebu, Philippines",
            "global_code": "7Q258W94+94"
        },
        "price_level": 3,
        "rating": 4.5,
        "reference": "ChIJtbwl9z6ZqTMRre9Ge6vIbz0",
        "scope": "GOOGLE",
        "types": [
            "restaurant",
            "food",
            "point_of_interest",
            "establishment"
        ],
        "user_ratings_total": 1787,
        "vicinity": "Ground level, The Terraces Ayala Center Cebu, 6000, Cebu City"
    },
    {
        "business_status": "OPERATIONAL",
        "geometry": {
            "location": {
                "lat": 10.3095044,
                "lng": 123.8938985
            },
            "viewport": {
                "northeast": {
                    "lat": 10.3108792802915,
                    "lng": 123.8951751802915
                },
                "southwest": {
                    "lat": 10.3081813197085,
                    "lng": 123.8924772197085
                }
            }
        },
        "icon": "https://maps.gstatic.com/mapfiles/place_api/icons/v1/png_71/restaurant-71.png",
        "icon_background_color": "#FF9E67",
        "icon_mask_base_uri": "https://maps.gstatic.com/mapfiles/place_api/icons/v2/restaurant_pinlet",
        "name": "Shakey's Pizza Parlor",
        "opening_hours": {
            "open_now": false
        },
        "photos": [
            {
                "height": 3024,
                "html_attributions": [
                    "<a href=\"https://maps.google.com/maps/contrib/107542254154407460377\">Wannabthat Girl</a>"
                ],
                "photo_reference": "ATJ83zgSXwqpF9ynv9mqQ7ZE6bAP3mmsPm6Ut52MQqG24SbC_hlUiffG1KCNDcrWICE0gZqskItp2Gleu_PMm1VF0pdBc4baYfHnXl0ur_RV3yVakgr6UNE5qA6JjFhvRt8DtX-RaDqrvC0Eu6QZAEncJfw_zG1px77w0ApTNwSfuIcxHc-i",
                "width": 4032
            }
        ],
        "place_id": "ChIJN7qFUk6ZqTMRd4QDzwClHvQ",
        "price_level": 2,
        "rating": 4.5,
        "reference": "ChIJN7qFUk6ZqTMRd4QDzwClHvQ",
        "scope": "GOOGLE",
        "types": [
            "restaurant",
            "food",
            "point_of_interest",
            "establishment"
        ],
        "user_ratings_total": 10,
        "vicinity": "8V5V+RH2, Fuente Osmeña Circle, Cebu City"
    },
    {
        "business_status": "OPERATIONAL",
        "geometry": {
            "location": {
                "lat": 10.3114079,
                "lng": 123.8949466
            },
            "viewport": {
                "northeast": {
                    "lat": 10.3127793802915,
                    "lng": 123.8964233302915
                },
                "southwest": {
                    "lat": 10.3100814197085,
                    "lng": 123.8937253697085
                }
            }
        },
        "icon": "https://maps.gstatic.com/mapfiles/place_api/icons/v1/png_71/restaurant-71.png",
        "icon_background_color": "#FF9E67",
        "icon_mask_base_uri": "https://maps.gstatic.com/mapfiles/place_api/icons/v2/restaurant_pinlet",
        "name": "Muvanz Pocherohan And Seafoods",
        "opening_hours": {
            "open_now": true
        },
        "photos": [
            {
                "height": 4032,
                "html_attributions": [
                    "<a href=\"https://maps.google.com/maps/contrib/118238539255650076957\">Cronz Nadera</a>"
                ],
                "photo_reference": "ATJ83zj1fzglWBwhLeH_gFh1MHYf2iv70xFVYbNhrxNDA_9jclSLLs8eFPSNw00BuVZfA-_j8qaxarBLMjvD8anqh7Zc9LIzy0CXIk30S3YgHxMqYu98xG5V-ut237vJVT8eUS0Tfm5HsGwxQFPfrqqFCxoVHu8pLmF0d5IQyk5KtyAPSBV4",
                "width": 3024
            }
        ],
        "place_id": "ChIJT3n9ME-ZqTMRHq-qls45sK4",
        "plus_code": {
            "compound_code": "8V6V+HX Cebu City, Cebu, Philippines",
            "global_code": "7Q258V6V+HX"
        },
        "price_level": 1,
        "rating": 4.1,
        "reference": "ChIJT3n9ME-ZqTMRHq-qls45sK4",
        "scope": "GOOGLE",
        "types": [
            "meal_takeaway",
            "restaurant",
            "food",
            "point_of_interest",
            "establishment"
        ],
        "user_ratings_total": 558,
        "vicinity": "Century Plaza Complex, Juana Osmeña Street, Cebu City"
    },
    {
        "business_status": "OPERATIONAL",
        "geometry": {
            "location": {
                "lat": 10.3200254,
                "lng": 123.9026177
            },
            "viewport": {
                "northeast": {
                    "lat": 10.3213067802915,
                    "lng": 123.9040007302915
                },
                "southwest": {
                    "lat": 10.3186088197085,
                    "lng": 123.9013027697085
                }
            }
        },
        "icon": "https://maps.gstatic.com/mapfiles/place_api/icons/v1/png_71/restaurant-71.png",
        "icon_background_color": "#FF9E67",
        "icon_mask_base_uri": "https://maps.gstatic.com/mapfiles/place_api/icons/v2/restaurant_pinlet",
        "name": "Sinangag Station",
        "opening_hours": {
            "open_now": false
        },
        "photos": [
            {
                "height": 3000,
                "html_attributions": [
                    "<a href=\"https://maps.google.com/maps/contrib/109354592969165963805\">Jessie James Gumisad</a>"
                ],
                "photo_reference": "ATJ83zjo1wZJ08rLpV7MTJNG7IB1Z6EzF9kygws8GP2MF5KpO0M_s4k2ZEXDrAeUHpgvFGJHfzDW0Ju1pqmCtLSj0np2sR1kfU7mRmvB8rYtMxLY7UrW9c1XUOFhkhrYsiPQZutaZCOOCE3VfuxDo_qxWw1rfa88wry0UjamtROVgc8oEJRh",
                "width": 5333
            }
        ],
        "place_id": "ChIJoaIOsz6ZqTMRYrKg9L5mMjk",
        "rating": 4.1,
        "reference": "ChIJoaIOsz6ZqTMRYrKg9L5mMjk",
        "scope": "GOOGLE",
        "types": [
            "restaurant",
            "food",
            "point_of_interest",
            "establishment"
        ],
        "user_ratings_total": 120,
        "vicinity": "8WC3+229, North Escario Street, Cebu City"
    },
    {
        "business_status": "CLOSED_TEMPORARILY",
        "geometry": {
            "location": {
                "lat": 10.3116761,
                "lng": 123.9004669
            },
            "viewport": {
                "northeast": {
                    "lat": 10.3129801802915,
                    "lng": 123.9017757302915
                },
                "southwest": {
                    "lat": 10.3102822197085,
                    "lng": 123.8990777697085
                }
            }
        },
        "icon": "https://maps.gstatic.com/mapfiles/place_api/icons/v1/png_71/restaurant-71.png",
        "icon_background_color": "#FF9E67",
        "icon_mask_base_uri": "https://maps.gstatic.com/mapfiles/place_api/icons/v2/restaurant_pinlet",
        "name": "KOA Tree House",
        "permanently_closed": true,
        "photos": [
            {
                "height": 2976,
                "html_attributions": [
                    "<a href=\"https://maps.google.com/maps/contrib/112811375566120793869\">Jhannski Cirilo</a>"
                ],
                "photo_reference": "ATJ83zgtgtLNPMJki5_r5BOY1oYiD01iGJj50roz7jahrsVTTe-0X6cF_UysYrGUdH_T-XRZq-45kw5whHb-JQNcKlvtmtVSudyxQaNzXdFdf9GG_3jnk6MO0wWNU_sq2Usr45kj-asKlilqpLEhENSsqktvI1arBd2FGZ0qNaiTCDz0FRff",
                "width": 3968
            }
        ],
        "place_id": "ChIJ-yz5ATmZqTMRY4kfg-KvNWA",
        "plus_code": {
            "compound_code": "8W62+M5 Cebu City, Cebu, Philippines",
            "global_code": "7Q258W62+M5"
        },
        "rating": 4,
        "reference": "ChIJ-yz5ATmZqTMRY4kfg-KvNWA",
        "scope": "GOOGLE",
        "types": [
            "restaurant",
            "food",
            "point_of_interest",
            "establishment"
        ],
        "user_ratings_total": 201,
        "vicinity": "The River Gate Complex, Cebu City"
    }
 ]
}